{
  "consumer": {
    "name": "api-gateway"
  },
  "interactions": [
    {
      "description": "la validation d’une semaine A_VALIDER",
      "providerStates": [
        {
          "name": "une semaine A_VALIDER existe pour validation"
        }
      ],
      "request": {
        "method": "POST",
        "path": "/api/validations/55555555-0000-4000-8000-000000000000/2026-W10"
      },
      "response": {
        "body": {
          "contratId": "55555555-0000-4000-8000-000000000000",
          "deltaModifs": null,
          "semaineIso": "2026-W10",
          "statut": "VALIDEE"
        },
        "headers": {
          "Content-Type": "application/json; charset=utf-8"
        },
        "matchingRules": {
          "body": {
            "$.contratId": {
              "combine": "AND",
              "matchers": [
                {
                  "match": "type"
                }
              ]
            },
            "$.semaineIso": {
              "combine": "AND",
              "matchers": [
                {
                  "match": "type"
                }
              ]
            },
            "$.statut": {
              "combine": "AND",
              "matchers": [
                {
                  "match": "type"
                }
              ]
            }
          }
        },
        "status": 200
      }
    },
    {
      "description": "un envoi du récap agrégé par établissement",
      "providerStates": [
        {
          "name": "un récap agrégé par établissement est prêt à envoyer au service"
        }
      ],
      "request": {
        "body": {
          "etablissementId": "99999999-9999-4999-8999-999999999999",
          "foyerId": "22222222-2222-4222-8222-222222222222",
          "semaineIso": "2026-W10"
        },
        "headers": {
          "Content-Type": "application/json; charset=utf-8"
        },
        "method": "POST",
        "path": "/api/envois/etablissement"
      },
      "response": {
        "body": {
          "destinataire": "contact-creche@example.org",
          "envoyeLe": "2026-03-09T08:00:00.000Z",
          "erreur": null,
          "etablissementId": "99999999-9999-4999-8999-999999999999",
          "foyerId": "22222222-2222-4222-8222-222222222222",
          "messageId": null,
          "semaineIso": "2026-W10",
          "statut": "DRY_RUN"
        },
        "headers": {
          "Content-Type": "application/json; charset=utf-8"
        },
        "matchingRules": {
          "body": {
            "$.destinataire": {
              "combine": "AND",
              "matchers": [
                {
                  "match": "type"
                }
              ]
            },
            "$.envoyeLe": {
              "combine": "AND",
              "matchers": [
                {
                  "match": "type"
                }
              ]
            },
            "$.etablissementId": {
              "combine": "AND",
              "matchers": [
                {
                  "match": "type"
                }
              ]
            },
            "$.foyerId": {
              "combine": "AND",
              "matchers": [
                {
                  "match": "type"
                }
              ]
            },
            "$.semaineIso": {
              "combine": "AND",
              "matchers": [
                {
                  "match": "type"
                }
              ]
            },
            "$.statut": {
              "combine": "AND",
              "matchers": [
                {
                  "match": "type"
                }
              ]
            }
          }
        },
        "status": 200
      }
    },
    {
      "description": "une lecture des semaines à valider d’un foyer",
      "providerStates": [
        {
          "name": "une semaine est à valider pour un foyer"
        }
      ],
      "request": {
        "method": "GET",
        "path": "/api/validations/a-valider",
        "query": {
          "foyer": [
            "22222222-2222-4222-8222-222222222222"
          ]
        }
      },
      "response": {
        "body": [
          {
            "contratId": "55555555-0000-4000-8000-000000000000",
            "foyerId": "22222222-2222-4222-8222-222222222222",
            "notifieeLe": "2026-06-23T06:00:00.000Z",
            "semaineIso": "2026-W10",
            "statut": "A_VALIDER"
          }
        ],
        "headers": {
          "Content-Type": "application/json; charset=utf-8"
        },
        "matchingRules": {
          "body": {
            "$": {
              "combine": "AND",
              "matchers": [
                {
                  "match": "type",
                  "min": 1
                }
              ]
            },
            "$[*].contratId": {
              "combine": "AND",
              "matchers": [
                {
                  "match": "type"
                }
              ]
            },
            "$[*].foyerId": {
              "combine": "AND",
              "matchers": [
                {
                  "match": "type"
                }
              ]
            },
            "$[*].notifieeLe": {
              "combine": "AND",
              "matchers": [
                {
                  "match": "type"
                }
              ]
            },
            "$[*].semaineIso": {
              "combine": "AND",
              "matchers": [
                {
                  "match": "type"
                }
              ]
            },
            "$[*].statut": {
              "combine": "AND",
              "matchers": [
                {
                  "match": "type"
                }
              ]
            }
          }
        },
        "status": 200
      }
    },
    {
      "description": "une régénération du brouillon agrégé d’un établissement archivé",
      "providerStates": [
        {
          "name": "un brouillon agrégé pour un établissement archivé est disponible"
        }
      ],
      "request": {
        "method": "GET",
        "path": "/api/validations/semaine/22222222-2222-4222-8222-222222222222/2026-W10/etablissements/99999999-9999-4999-8999-999999999997/brouillon"
      },
      "response": {
        "body": {
          "corps": "<p>Bonjour Crèche Les Coccinelles,</p>",
          "destinataire": "",
          "dryRun": false,
          "enfants": [
            {
              "contratId": "55555555-0000-4000-8000-000000000003",
              "deltaModifs": {
                "jours": [
                  {
                    "date": "2026-03-04"
                  }
                ]
              },
              "enfant": "Nina"
            }
          ],
          "etablissementId": "99999999-9999-4999-8999-999999999997",
          "etablissementLibelle": "Crèche Les Coccinelles",
          "foyerId": "22222222-2222-4222-8222-222222222222",
          "raisonNonRoutable": "ARCHIVE",
          "routable": false,
          "semaineIso": "2026-W10",
          "sujet": "Plannings modifiés — semaine 2026-W10",
          "texte": "Bonjour Crèche Les Coccinelles,"
        },
        "headers": {
          "Content-Type": "application/json; charset=utf-8"
        },
        "matchingRules": {
          "body": {
            "$.corps": {
              "combine": "AND",
              "matchers": [
                {
                  "match": "type"
                }
              ]
            },
            "$.dryRun": {
              "combine": "AND",
              "matchers": [
                {
                  "match": "type"
                }
              ]
            },
            "$.enfants": {
              "combine": "AND",
              "matchers": [
                {
                  "match": "type",
                  "min": 1
                }
              ]
            },
            "$.enfants[*].contratId": {
              "combine": "AND",
              "matchers": [
                {
                  "match": "type"
                }
              ]
            },
            "$.enfants[*].deltaModifs.jours": {
              "combine": "AND",
              "matchers": [
                {
                  "match": "type",
                  "min": 1
                }
              ]
            },
            "$.enfants[*].deltaModifs.jours[*].date": {
              "combine": "AND",
              "matchers": [
                {
                  "match": "type"
                }
              ]
            },
            "$.enfants[*].enfant": {
              "combine": "AND",
              "matchers": [
                {
                  "match": "type"
                }
              ]
            },
            "$.etablissementId": {
              "combine": "AND",
              "matchers": [
                {
                  "match": "type"
                }
              ]
            },
            "$.etablissementLibelle": {
              "combine": "AND",
              "matchers": [
                {
                  "match": "type"
                }
              ]
            },
            "$.foyerId": {
              "combine": "AND",
              "matchers": [
                {
                  "match": "type"
                }
              ]
            },
            "$.raisonNonRoutable": {
              "combine": "AND",
              "matchers": [
                {
                  "match": "type"
                }
              ]
            },
            "$.routable": {
              "combine": "AND",
              "matchers": [
                {
                  "match": "type"
                }
              ]
            },
            "$.semaineIso": {
              "combine": "AND",
              "matchers": [
                {
                  "match": "type"
                }
              ]
            },
            "$.sujet": {
              "combine": "AND",
              "matchers": [
                {
                  "match": "type"
                }
              ]
            },
            "$.texte": {
              "combine": "AND",
              "matchers": [
                {
                  "match": "type"
                }
              ]
            }
          }
        },
        "status": 200
      }
    },
    {
      "description": "une régénération du brouillon agrégé d’un établissement sans e-mail",
      "providerStates": [
        {
          "name": "un brouillon agrégé pour un établissement sans e-mail est disponible"
        }
      ],
      "request": {
        "method": "GET",
        "path": "/api/validations/semaine/22222222-2222-4222-8222-222222222222/2026-W10/etablissements/99999999-9999-4999-8999-999999999998/brouillon"
      },
      "response": {
        "body": {
          "corps": "<p>Bonjour Halte-garderie du Parc,</p>",
          "destinataire": "",
          "dryRun": false,
          "enfants": [
            {
              "contratId": "55555555-0000-4000-8000-000000000002",
              "deltaModifs": {
                "jours": [
                  {
                    "date": "2026-03-04"
                  }
                ]
              },
              "enfant": "Zoé"
            }
          ],
          "etablissementId": "99999999-9999-4999-8999-999999999998",
          "etablissementLibelle": "Halte-garderie du Parc",
          "foyerId": "22222222-2222-4222-8222-222222222222",
          "raisonNonRoutable": "SANS_EMAIL",
          "routable": false,
          "semaineIso": "2026-W10",
          "sujet": "Plannings modifiés — semaine 2026-W10",
          "texte": "Bonjour Halte-garderie du Parc,"
        },
        "headers": {
          "Content-Type": "application/json; charset=utf-8"
        },
        "matchingRules": {
          "body": {
            "$.corps": {
              "combine": "AND",
              "matchers": [
                {
                  "match": "type"
                }
              ]
            },
            "$.dryRun": {
              "combine": "AND",
              "matchers": [
                {
                  "match": "type"
                }
              ]
            },
            "$.enfants": {
              "combine": "AND",
              "matchers": [
                {
                  "match": "type",
                  "min": 1
                }
              ]
            },
            "$.enfants[*].contratId": {
              "combine": "AND",
              "matchers": [
                {
                  "match": "type"
                }
              ]
            },
            "$.enfants[*].deltaModifs.jours": {
              "combine": "AND",
              "matchers": [
                {
                  "match": "type",
                  "min": 1
                }
              ]
            },
            "$.enfants[*].deltaModifs.jours[*].date": {
              "combine": "AND",
              "matchers": [
                {
                  "match": "type"
                }
              ]
            },
            "$.enfants[*].enfant": {
              "combine": "AND",
              "matchers": [
                {
                  "match": "type"
                }
              ]
            },
            "$.etablissementId": {
              "combine": "AND",
              "matchers": [
                {
                  "match": "type"
                }
              ]
            },
            "$.etablissementLibelle": {
              "combine": "AND",
              "matchers": [
                {
                  "match": "type"
                }
              ]
            },
            "$.foyerId": {
              "combine": "AND",
              "matchers": [
                {
                  "match": "type"
                }
              ]
            },
            "$.raisonNonRoutable": {
              "combine": "AND",
              "matchers": [
                {
                  "match": "type"
                }
              ]
            },
            "$.routable": {
              "combine": "AND",
              "matchers": [
                {
                  "match": "type"
                }
              ]
            },
            "$.semaineIso": {
              "combine": "AND",
              "matchers": [
                {
                  "match": "type"
                }
              ]
            },
            "$.sujet": {
              "combine": "AND",
              "matchers": [
                {
                  "match": "type"
                }
              ]
            },
            "$.texte": {
              "combine": "AND",
              "matchers": [
                {
                  "match": "type"
                }
              ]
            }
          }
        },
        "status": 200
      }
    },
    {
      "description": "une régénération du brouillon agrégé par établissement",
      "providerStates": [
        {
          "name": "un brouillon de mail agrégé par établissement est disponible"
        }
      ],
      "request": {
        "method": "GET",
        "path": "/api/validations/semaine/22222222-2222-4222-8222-222222222222/2026-W10/etablissements/99999999-9999-4999-8999-999999999999/brouillon"
      },
      "response": {
        "body": {
          "corps": "<p>Bonjour Crèche Les Hirondelles,</p>",
          "destinataire": "contact-creche@example.org",
          "dryRun": true,
          "enfants": [
            {
              "contratId": "55555555-0000-4000-8000-000000000000",
              "deltaModifs": {
                "jours": [
                  {
                    "date": "2026-03-04"
                  }
                ]
              },
              "enfant": "Léa"
            }
          ],
          "etablissementId": "99999999-9999-4999-8999-999999999999",
          "etablissementLibelle": "Crèche Les Hirondelles",
          "foyerId": "22222222-2222-4222-8222-222222222222",
          "raisonNonRoutable": null,
          "routable": true,
          "semaineIso": "2026-W10",
          "sujet": "Plannings modifiés — semaine 2026-W10",
          "texte": "Bonjour Crèche Les Hirondelles,"
        },
        "headers": {
          "Content-Type": "application/json; charset=utf-8"
        },
        "matchingRules": {
          "body": {
            "$.corps": {
              "combine": "AND",
              "matchers": [
                {
                  "match": "type"
                }
              ]
            },
            "$.destinataire": {
              "combine": "AND",
              "matchers": [
                {
                  "match": "type"
                }
              ]
            },
            "$.dryRun": {
              "combine": "AND",
              "matchers": [
                {
                  "match": "type"
                }
              ]
            },
            "$.enfants": {
              "combine": "AND",
              "matchers": [
                {
                  "match": "type",
                  "min": 1
                }
              ]
            },
            "$.enfants[*].contratId": {
              "combine": "AND",
              "matchers": [
                {
                  "match": "type"
                }
              ]
            },
            "$.enfants[*].deltaModifs.jours": {
              "combine": "AND",
              "matchers": [
                {
                  "match": "type",
                  "min": 1
                }
              ]
            },
            "$.enfants[*].deltaModifs.jours[*].date": {
              "combine": "AND",
              "matchers": [
                {
                  "match": "type"
                }
              ]
            },
            "$.enfants[*].enfant": {
              "combine": "AND",
              "matchers": [
                {
                  "match": "type"
                }
              ]
            },
            "$.etablissementId": {
              "combine": "AND",
              "matchers": [
                {
                  "match": "type"
                }
              ]
            },
            "$.etablissementLibelle": {
              "combine": "AND",
              "matchers": [
                {
                  "match": "type"
                }
              ]
            },
            "$.foyerId": {
              "combine": "AND",
              "matchers": [
                {
                  "match": "type"
                }
              ]
            },
            "$.routable": {
              "combine": "AND",
              "matchers": [
                {
                  "match": "type"
                }
              ]
            },
            "$.semaineIso": {
              "combine": "AND",
              "matchers": [
                {
                  "match": "type"
                }
              ]
            },
            "$.sujet": {
              "combine": "AND",
              "matchers": [
                {
                  "match": "type"
                }
              ]
            },
            "$.texte": {
              "combine": "AND",
              "matchers": [
                {
                  "match": "type"
                }
              ]
            }
          }
        },
        "status": 200
      }
    }
  ],
  "metadata": {
    "pact-js": {
      "version": "17.0.1"
    },
    "pactRust": {
      "ffi": "0.5.4",
      "models": "1.3.11"
    },
    "pactSpecification": {
      "version": "3.0.0"
    }
  },
  "provider": {
    "name": "svc-notifications"
  }
}